scr/GANNA1/GANNA1.py
scr/GANNA1/__init__.py
scr/GANNA1/.ipynb_checkpoints/Untitled-checkpoint.ipynb
scr/GANNA1/.ipynb_checkpoints/Untitled1-checkpoint.ipynb
scr/GANNA1/.ipynb_checkpoints/gen_str-checkpoint.py
ganna1-0.0.1.dist-info/METADATA
ganna1-0.0.1.dist-info/WHEEL
ganna1-0.0.1.dist-info/licenses/LICENSE
ganna1-0.0.1.dist-info/RECORD
